<?xml version="1.0" encoding="UTF-16"?>
<TextureAtlas imagePath="Mae_Assets.png">
	<!-- Created with Adobe Flash CS6 version 12.0.0.481 -->
	<!-- http://www.adobe.com/products/flash.html -->
	<SubTexture name="mae down0000" x="1" y="1" width="679" height="486" frameX="0" frameY="-6" frameWidth="679" frameHeight="492"/>
	<SubTexture name="mae down0001" x="1" y="1" width="679" height="486" frameX="0" frameY="-6" frameWidth="679" frameHeight="492"/>
	<SubTexture name="mae down0002" x="683" y="1" width="659" height="484" frameX="0" frameY="-7" frameWidth="679" frameHeight="492"/>
	<SubTexture name="mae down0003" x="683" y="1" width="659" height="484" frameX="0" frameY="-7" frameWidth="679" frameHeight="492"/>
	<SubTexture name="mae down0004" x="1345" y="1" width="654" height="491" frameX="0" frameY="0" frameWidth="679" frameHeight="492"/>
	<SubTexture name="mae down0005" x="2002" y="1" width="654" height="491" frameX="0" frameY="0" frameWidth="679" frameHeight="492"/>
	<SubTexture name="mae down0006" x="2002" y="1" width="654" height="491" frameX="0" frameY="0" frameWidth="679" frameHeight="492"/>
	<SubTexture name="mae down0007" x="2002" y="1" width="654" height="491" frameX="0" frameY="0" frameWidth="679" frameHeight="492"/>
	<SubTexture name="mae down0008" x="2002" y="1" width="654" height="491" frameX="0" frameY="0" frameWidth="679" frameHeight="492"/>
	<SubTexture name="mae down0009" x="2002" y="1" width="654" height="491" frameX="0" frameY="0" frameWidth="679" frameHeight="492"/>
	<SubTexture name="mae down0010" x="2002" y="1" width="654" height="491" frameX="0" frameY="0" frameWidth="679" frameHeight="492"/>
	<SubTexture name="mae down0011" x="2002" y="1" width="654" height="491" frameX="0" frameY="0" frameWidth="679" frameHeight="492"/>
	<SubTexture name="mae down0012" x="2002" y="1" width="654" height="491" frameX="0" frameY="0" frameWidth="679" frameHeight="492"/>
	<SubTexture name="mae down0013" x="2002" y="1" width="654" height="491" frameX="0" frameY="0" frameWidth="679" frameHeight="492"/>
	<SubTexture name="mae down0014" x="2002" y="1" width="654" height="491" frameX="0" frameY="0" frameWidth="679" frameHeight="492"/>
	<SubTexture name="mae idle0000" x="2659" y="1" width="631" height="491" frameX="0" frameY="-13" frameWidth="631" frameHeight="504"/>
	<SubTexture name="mae idle0001" x="2659" y="1" width="631" height="491" frameX="0" frameY="-13" frameWidth="631" frameHeight="504"/>
	<SubTexture name="mae idle0002" x="3293" y="1" width="631" height="494" frameX="0" frameY="-10" frameWidth="631" frameHeight="504"/>
	<SubTexture name="mae idle0003" x="3293" y="1" width="631" height="494" frameX="0" frameY="-10" frameWidth="631" frameHeight="504"/>
	<SubTexture name="mae idle0004" x="1" y="498" width="631" height="497" frameX="0" frameY="-7" frameWidth="631" frameHeight="504"/>
	<SubTexture name="mae idle0005" x="635" y="498" width="631" height="497" frameX="0" frameY="-7" frameWidth="631" frameHeight="504"/>
	<SubTexture name="mae idle0006" x="1269" y="498" width="631" height="502" frameX="0" frameY="-2" frameWidth="631" frameHeight="504"/>
	<SubTexture name="mae idle0007" x="1269" y="498" width="631" height="502" frameX="0" frameY="-2" frameWidth="631" frameHeight="504"/>
	<SubTexture name="mae idle0008" x="1903" y="498" width="631" height="504"/>
	<SubTexture name="mae idle0009" x="1903" y="498" width="631" height="504"/>
	<SubTexture name="mae idle0010" x="1903" y="498" width="631" height="504"/>
	<SubTexture name="mae idle0011" x="1903" y="498" width="631" height="504"/>
	<SubTexture name="mae idle0012" x="1903" y="498" width="631" height="504"/>
	<SubTexture name="mae idle0013" x="1903" y="498" width="631" height="504"/>
	<SubTexture name="mae idle0014" x="1903" y="498" width="631" height="504"/>
	<SubTexture name="mae left0000" x="2537" y="498" width="631" height="515"/>
	<SubTexture name="mae left0001" x="2537" y="498" width="631" height="515"/>
	<SubTexture name="mae left0002" x="3171" y="498" width="631" height="501" frameX="0" frameY="-11" frameWidth="631" frameHeight="515"/>
	<SubTexture name="mae left0003" x="3171" y="498" width="631" height="501" frameX="0" frameY="-11" frameWidth="631" frameHeight="515"/>
	<SubTexture name="mae left0004" x="1" y="1016" width="631" height="495" frameX="0" frameY="-16" frameWidth="631" frameHeight="515"/>
	<SubTexture name="mae left0005" x="635" y="1016" width="631" height="495" frameX="0" frameY="-16" frameWidth="631" frameHeight="515"/>
	<SubTexture name="mae left0006" x="635" y="1016" width="631" height="495" frameX="0" frameY="-16" frameWidth="631" frameHeight="515"/>
	<SubTexture name="mae left0007" x="635" y="1016" width="631" height="495" frameX="0" frameY="-16" frameWidth="631" frameHeight="515"/>
	<SubTexture name="mae left0008" x="635" y="1016" width="631" height="495" frameX="0" frameY="-16" frameWidth="631" frameHeight="515"/>
	<SubTexture name="mae left0009" x="635" y="1016" width="631" height="495" frameX="0" frameY="-16" frameWidth="631" frameHeight="515"/>
	<SubTexture name="mae left0010" x="635" y="1016" width="631" height="495" frameX="0" frameY="-16" frameWidth="631" frameHeight="515"/>
	<SubTexture name="mae left0011" x="635" y="1016" width="631" height="495" frameX="0" frameY="-16" frameWidth="631" frameHeight="515"/>
	<SubTexture name="mae left0012" x="635" y="1016" width="631" height="495" frameX="0" frameY="-16" frameWidth="631" frameHeight="515"/>
	<SubTexture name="mae left0013" x="635" y="1016" width="631" height="495" frameX="0" frameY="-16" frameWidth="631" frameHeight="515"/>
	<SubTexture name="mae left0014" x="635" y="1016" width="631" height="495" frameX="0" frameY="-16" frameWidth="631" frameHeight="515"/>
	<SubTexture name="mae right0000" x="1269" y="1016" width="631" height="514" frameX="0" frameY="-1" frameWidth="631" frameHeight="515"/>
	<SubTexture name="mae right0001" x="1269" y="1016" width="631" height="514" frameX="0" frameY="-1" frameWidth="631" frameHeight="515"/>
	<SubTexture name="mae right0002" x="1903" y="1016" width="631" height="515"/>
	<SubTexture name="mae right0003" x="1903" y="1016" width="631" height="515"/>
	<SubTexture name="mae right0004" x="2537" y="1016" width="631" height="511" frameX="0" frameY="-4" frameWidth="631" frameHeight="515"/>
	<SubTexture name="mae right0005" x="3171" y="1016" width="631" height="511" frameX="0" frameY="-4" frameWidth="631" frameHeight="515"/>
	<SubTexture name="mae right0006" x="3171" y="1016" width="631" height="511" frameX="0" frameY="-4" frameWidth="631" frameHeight="515"/>
	<SubTexture name="mae right0007" x="3171" y="1016" width="631" height="511" frameX="0" frameY="-4" frameWidth="631" frameHeight="515"/>
	<SubTexture name="mae right0008" x="3171" y="1016" width="631" height="511" frameX="0" frameY="-4" frameWidth="631" frameHeight="515"/>
	<SubTexture name="mae right0009" x="3171" y="1016" width="631" height="511" frameX="0" frameY="-4" frameWidth="631" frameHeight="515"/>
	<SubTexture name="mae right0010" x="3171" y="1016" width="631" height="511" frameX="0" frameY="-4" frameWidth="631" frameHeight="515"/>
	<SubTexture name="mae right0011" x="3171" y="1016" width="631" height="511" frameX="0" frameY="-4" frameWidth="631" frameHeight="515"/>
	<SubTexture name="mae right0012" x="3171" y="1016" width="631" height="511" frameX="0" frameY="-4" frameWidth="631" frameHeight="515"/>
	<SubTexture name="mae right0013" x="3171" y="1016" width="631" height="511" frameX="0" frameY="-4" frameWidth="631" frameHeight="515"/>
	<SubTexture name="mae right0014" x="3171" y="1016" width="631" height="511" frameX="0" frameY="-4" frameWidth="631" frameHeight="515"/>
	<SubTexture name="mae up0000" x="1" y="1534" width="631" height="532"/>
	<SubTexture name="mae up0001" x="1" y="1534" width="631" height="532"/>
	<SubTexture name="mae up0002" x="635" y="1534" width="631" height="518" frameX="0" frameY="-14" frameWidth="631" frameHeight="532"/>
	<SubTexture name="mae up0003" x="635" y="1534" width="631" height="518" frameX="0" frameY="-14" frameWidth="631" frameHeight="532"/>
	<SubTexture name="mae up0004" x="1269" y="1534" width="631" height="512" frameX="0" frameY="-20" frameWidth="631" frameHeight="532"/>
	<SubTexture name="mae up0005" x="1903" y="1534" width="631" height="512" frameX="0" frameY="-20" frameWidth="631" frameHeight="532"/>
	<SubTexture name="mae up0006" x="1903" y="1534" width="631" height="512" frameX="0" frameY="-20" frameWidth="631" frameHeight="532"/>
	<SubTexture name="mae up0007" x="1903" y="1534" width="631" height="512" frameX="0" frameY="-20" frameWidth="631" frameHeight="532"/>
	<SubTexture name="mae up0008" x="1903" y="1534" width="631" height="512" frameX="0" frameY="-20" frameWidth="631" frameHeight="532"/>
	<SubTexture name="mae up0009" x="1903" y="1534" width="631" height="512" frameX="0" frameY="-20" frameWidth="631" frameHeight="532"/>
	<SubTexture name="mae up0010" x="1903" y="1534" width="631" height="512" frameX="0" frameY="-20" frameWidth="631" frameHeight="532"/>
	<SubTexture name="mae up0011" x="1903" y="1534" width="631" height="512" frameX="0" frameY="-20" frameWidth="631" frameHeight="532"/>
	<SubTexture name="mae up0012" x="1903" y="1534" width="631" height="512" frameX="0" frameY="-20" frameWidth="631" frameHeight="532"/>
	<SubTexture name="mae up0013" x="1903" y="1534" width="631" height="512" frameX="0" frameY="-20" frameWidth="631" frameHeight="532"/>
	<SubTexture name="mae up0014" x="1903" y="1534" width="631" height="512" frameX="0" frameY="-20" frameWidth="631" frameHeight="532"/>
</TextureAtlas>
